frasco_eu_vat.py
setup.py
frasco_eu_vat.egg-info/PKG-INFO
frasco_eu_vat.egg-info/SOURCES.txt
frasco_eu_vat.egg-info/dependency_links.txt
frasco_eu_vat.egg-info/not-zip-safe
frasco_eu_vat.egg-info/requires.txt
frasco_eu_vat.egg-info/top_level.txt