Metadata-Version: 1.0
Name: frasco-eu-vat
Version: 0.3.2
Summary: EU VAT utilities for Frasco
Home-page: http://github.com/frascoweb/frasco-eu-vat
Author: Maxime Bouroumeau-Fuseau
Author-email: maxime.bouroumeau@gmail.com
License: MIT
Platform: any
